model/__init__.py
model/pymongo_model.py
pymongo_model-2.0.0.dist-info/LICENSE
pymongo_model-2.0.0.dist-info/METADATA
pymongo_model-2.0.0.dist-info/WHEEL
pymongo_model-2.0.0.dist-info/top_level.txt
pymongo_model-2.0.0.dist-info/RECORD
