Metadata-Version: 2.1
Name: pymongo-model
Version: 2.0.0
Summary: Simple model based usage of pymongo, also provides optional feature for tracking mongoDB document history
Home-page: https://github.com/aa3pankaj/pymongo-model
Author: Pankaj Singh
Author-email: aa3pankaj@gmail.com
License: UNKNOWN
Platform: UNKNOWN
Classifier: Programming Language :: Python :: 3
Classifier: License :: OSI Approved :: MIT License
Classifier: Operating System :: OS Independent
Requires-Python: >=3.6
Requires-Dist: jsondiff
Requires-Dist: pymongo
